nuance/__init__.py
nuance/core.py
nuance/kernels.py
nuance/linear_search.py
nuance/periodic_search.py
nuance/star.py
nuance/utils.py
nuance-0.8.1.dist-info/METADATA
nuance-0.8.1.dist-info/WHEEL
nuance-0.8.1.dist-info/licenses/LICENSE
nuance-0.8.1.dist-info/RECORD
