Metadata-Version: 2.3
Name: nuance
Version: 0.8.1
Summary: Transit signals detection among correlated noises
Author: Lionel Garcia
License-Expression: MIT
License-File: LICENSE
Keywords: astronomy,exoplanets,jax,transit
Classifier: Programming Language :: Python
Classifier: Programming Language :: Python :: 3
Requires-Python: >=3.9
Requires-Dist: jax>=0.4.25
Requires-Dist: jaxlib
Requires-Dist: jaxopt
Requires-Dist: matplotlib
Requires-Dist: multiprocess
Requires-Dist: numpy
Requires-Dist: scipy
Requires-Dist: tinygp
Requires-Dist: tqdm
Provides-Extra: dev
Requires-Dist: astropy; extra == 'dev'
Requires-Dist: black; extra == 'dev'
Requires-Dist: isort; extra == 'dev'
Requires-Dist: pytest; extra == 'dev'
Provides-Extra: docs
Requires-Dist: astropy; extra == 'docs'
Requires-Dist: docutils; extra == 'docs'
Requires-Dist: ipywidgets; extra == 'docs'
Requires-Dist: jupyterlab; extra == 'docs'
Requires-Dist: myst-nb; extra == 'docs'
Requires-Dist: myst-parser; extra == 'docs'
Requires-Dist: sphinx; extra == 'docs'
Requires-Dist: sphinx-book-theme; extra == 'docs'
Requires-Dist: sphinx-copybutton; extra == 'docs'
Requires-Dist: sphinx-design; extra == 'docs'
Requires-Dist: toml; extra == 'docs'
Requires-Dist: wotan; extra == 'docs'
